good_gpt/__init__.py
good_gpt/good_gpt.py
good_gpt/post_install.py
good_gpt-0.1.1.data/scripts/gg
good_gpt-0.1.1.dist-info/METADATA
good_gpt-0.1.1.dist-info/WHEEL
good_gpt-0.1.1.dist-info/entry_points.txt
good_gpt-0.1.1.dist-info/top_level.txt
good_gpt-0.1.1.dist-info/RECORD
