Metadata-Version: 2.1
Name: good-gpt
Version: 0.1.1
Summary: AI command line assistant. Describe a command and get the output.
Home-page: https://github.com/emilamaj/good-gpt
Author: Emile Amajar
License: MIT
Keywords: ai assistant openai gpt command-line terminal
Classifier: Development Status :: 4 - Beta
Classifier: Intended Audience :: Developers
Classifier: License :: OSI Approved :: MIT License
Classifier: Programming Language :: Python :: 3
Classifier: Programming Language :: Python :: 3.6
Classifier: Programming Language :: Python :: 3.7
Classifier: Programming Language :: Python :: 3.8
Classifier: Programming Language :: Python :: 3.9
Classifier: Programming Language :: Python :: 3.10
Classifier: Programming Language :: Python :: 3.11
Classifier: Programming Language :: Python :: 3.12
Classifier: Programming Language :: Python :: 3.13
Classifier: Topic :: Utilities
Classifier: Topic :: Terminals
Classifier: Topic :: System :: Shells
Classifier: Operating System :: Microsoft :: Windows
Classifier: Operating System :: MacOS
Classifier: Operating System :: POSIX :: Linux
Requires-Python: >=3.6
Requires-Dist: requests
